MANIFEST.in
README.rst
setup.py
aio/__init__.py
aio.signals.egg-info/PKG-INFO
aio.signals.egg-info/SOURCES.txt
aio.signals.egg-info/dependency_links.txt
aio.signals.egg-info/entry_points.txt
aio.signals.egg-info/namespace_packages.txt
aio.signals.egg-info/not-zip-safe
aio.signals.egg-info/requires.txt
aio.signals.egg-info/top_level.txt
aio/signals/README.rst
aio/signals/__init__.py
aio/signals/tests/__init__.py
aio/signals/tests/test_signals.py