Metadata-Version: 1.1
Name: aio.signals
Version: 0.1.1
Summary: Pubsub system for aio framework
Home-page: http://github.com/phlax/aio.signals
Author: Ryan Northey
Author-email: ryan@3ca.org.uk
License: GPL
Platform: UNKNOWN
Classifier: Development Status :: 4 - Beta
Classifier: Intended Audience :: Developers
Classifier: Programming Language :: Python :: 3.4
Classifier: Topic :: Software Development :: Libraries :: Python Modules
